pyobf2/__init__.py
pyobf2/__main__.py
pyobf2/lib/__init__.py
pyobf2/lib/assembler.py
pyobf2/lib/cfg.py
pyobf2/lib/log.py
pyobf2/lib/renamer.py
pyobf2/lib/transformers/__init__.py
pyobf2/lib/transformers/collector.py
pyobf2/lib/transformers/compileFinalFiles.py
pyobf2/lib/transformers/constructDynamicCodeObjTransformer.py
pyobf2/lib/transformers/encodeStringsTransformer.py
pyobf2/lib/transformers/floatsToComplex.py
pyobf2/lib/transformers/fstrToFormatTransformer.py
pyobf2/lib/transformers/intObfuscatorTransformer.py
pyobf2/lib/transformers/logicTransformer.py
pyobf2/lib/transformers/memberRenamerTransformer.py
pyobf2/lib/transformers/packPyz.py
pyobf2/lib/transformers/removeTypeHintsTransformer.py
pyobf2/lib/transformers/replaceAttribsTransformer.py
pyobf2/lib/transformers/stringCollectorTransformer.py
pyobf2/lib/transformers/typeAliasTransformer.py
pyobf2/lib/transformers/unicodeNameTransformer.py
pyobf2/lib/util.py
pyobf2-1.3.1.dist-info/LICENSE
pyobf2-1.3.1.dist-info/METADATA
pyobf2-1.3.1.dist-info/WHEEL
pyobf2-1.3.1.dist-info/entry_points.txt
pyobf2-1.3.1.dist-info/RECORD
