Metadata-Version: 2.1
Name: pyobf2
Version: 1.3.1
Summary: An in-place obfuscator for python 3.11
Home-page: https://github.com/0x3C50/pyobf2
Keywords: obfuscator,obfuscator-api
Author: 0x150
Author-email: 99053360+0x3C50@users.noreply.github.com
Requires-Python: >=3.10,<4.0
Classifier: Programming Language :: Python :: 3
Classifier: Programming Language :: Python :: 3.10
Classifier: Programming Language :: Python :: 3.11
Requires-Dist: colorama (>=0.4.6,<0.5.0)
Requires-Dist: pycryptodome (>=3.18.0,<4.0.0)
Requires-Dist: rich (>=13.4.1,<14.0.0)
Requires-Dist: tomlkit (>=0.11.8,<0.12.0)
Project-URL: Repository, https://github.com/0x3C50/pyobf2
